{
  "ZipCode": 93206,
  "Generated": "2025-06-02 16:42:57",
  "Project": "PGE_electric",
  "Years": {
    "2013": {
      "Elec- Agricultural": {
        "TotalkWh": 71789153.0,
        "TotalCustomers": 961,
        "Combined": 0.0
      },
      "Elec- Commercial": {
        "TotalkWh": 1474974.0,
        "TotalCustomers": 132,
        "Combined": 0.0
      },
      "Elec- Industrial": {
        "TotalkWh": 0.0,
        "TotalCustomers": 0,
        "Combined": 0.0
      },
      "Elec- Residential": {
        "TotalkWh": 6712832.0,
        "TotalCustomers": 7808,
        "Combined": 0.0
      }
    },
    "2014": {
      "Elec- Agricultural": {
        "TotalkWh": 0.0,
        "TotalCustomers": 0,
        "Combined": 0.0
      },
      "Elec- Commercial": {
        "TotalkWh": 0.0,
        "TotalCustomers": 0,
        "Combined": 0.0
      },
      "Elec- Industrial": {
        "TotalkWh": 0.0,
        "TotalCustomers": 0,
        "Combined": 0.0
      },
      "Elec- Residential": {
        "TotalkWh": 7696434.0,
        "TotalCustomers": 9307,
        "Combined": 0.0
      }
    },
    "2015": {
      "Elec- Agricultural": {
        "TotalkWh": 0.0,
        "TotalCustomers": 0,
        "Combined": 0.0
      },
      "Elec- Commercial": {
        "TotalkWh": 0.0,
        "TotalCustomers": 0,
        "Combined": 0.0
      },
      "Elec- Industrial": {
        "TotalkWh": 0.0,
        "TotalCustomers": 0,
        "Combined": 0.0
      },
      "Elec- Residential": {
        "TotalkWh": 5145561.0,
        "TotalCustomers": 6188,
        "Combined": 0.0
      }
    },
    "2016": {
      "Elec- Agricultural": {
        "TotalkWh": 58242484.0,
        "TotalCustomers": 1042,
        "Combined": 0.0
      },
      "Elec- Commercial": {
        "TotalkWh": 0.0,
        "TotalCustomers": 0,
        "Combined": 0.0
      },
      "Elec- Industrial": {
        "TotalkWh": 0.0,
        "TotalCustomers": 0,
        "Combined": 0.0
      },
      "Elec- Residential": {
        "TotalkWh": 4787945.0,
        "TotalCustomers": 6221,
        "Combined": 0.0
      }
    },
    "2017": {
      "Elec- Agricultural": {
        "TotalkWh": 8809508.0,
        "TotalCustomers": 302,
        "Combined": 0.0
      },
      "Elec- Commercial": {
        "TotalkWh": 0.0,
        "TotalCustomers": 0,
        "Combined": 0.0
      },
      "Elec- Industrial": {
        "TotalkWh": 0.0,
        "TotalCustomers": 0,
        "Combined": 0.0
      },
      "Elec- Residential": {
        "TotalkWh": 5364813.0,
        "TotalCustomers": 6767,
        "Combined": 0.0
      }
    },
    "2018": {
      "Elec- Agricultural": {
        "TotalkWh": 73505911.0,
        "TotalCustomers": 1198,
        "Combined": 0.0
      },
      "Elec- Commercial": {
        "TotalkWh": 0.0,
        "TotalCustomers": 0,
        "Combined": 0.0
      },
      "Elec- Industrial": {
        "TotalkWh": 0.0,
        "TotalCustomers": 0,
        "Combined": 0.0
      },
      "Elec- Residential": {
        "TotalkWh": 4726441.0,
        "TotalCustomers": 6376,
        "Combined": 0.0
      }
    },
    "2019": {
      "Elec- Agricultural": {
        "TotalkWh": 9136645.0,
        "TotalCustomers": 222,
        "Combined": 0.0
      },
      "Elec- Commercial": {
        "TotalkWh": 3168856.0,
        "TotalCustomers": 222,
        "Combined": 0.0
      },
      "Elec- Industrial": {
        "TotalkWh": 0.0,
        "TotalCustomers": 0,
        "Combined": 0.0
      },
      "Elec- Residential": {
        "TotalkWh": 4584527.0,
        "TotalCustomers": 6374,
        "Combined": 0.0
      }
    },
    "2020": {
      "Elec- Agricultural": {
        "TotalkWh": 87759613.0,
        "TotalCustomers": 1341,
        "Combined": 0.0
      },
      "Elec- Commercial": {
        "TotalkWh": 0.0,
        "TotalCustomers": 0,
        "Combined": 0.0
      },
      "Elec- Industrial": {
        "TotalkWh": 0.0,
        "TotalCustomers": 0,
        "Combined": 0.0
      },
      "Elec- Residential": {
        "TotalkWh": 5001016.0,
        "TotalCustomers": 6447,
        "Combined": 0.0
      }
    },
    "2021": {
      "Elec- Agricultural": {
        "TotalkWh": 60971757.0,
        "TotalCustomers": 630,
        "Combined": 0.0
      },
      "Elec- Commercial": {
        "TotalkWh": 0.0,
        "TotalCustomers": 0,
        "Combined": 0.0
      },
      "Elec- Industrial": {
        "TotalkWh": 0.0,
        "TotalCustomers": 0,
        "Combined": 0.0
      },
      "Elec- Residential": {
        "TotalkWh": 5298453.0,
        "TotalCustomers": 6486,
        "Combined": 0.0
      }
    },
    "2022": {
      "Elec- Agricultural": {
        "TotalkWh": 57734156.0,
        "TotalCustomers": 361,
        "Combined": 0.0
      },
      "Elec- Commercial": {
        "TotalkWh": 0.0,
        "TotalCustomers": 0,
        "Combined": 0.0
      },
      "Elec- Industrial": {
        "TotalkWh": 0.0,
        "TotalCustomers": 0,
        "Combined": 0.0
      },
      "Elec- Residential": {
        "TotalkWh": 5359458.0,
        "TotalCustomers": 6479,
        "Combined": 0.0
      }
    },
    "2023": {
      "Elec- Agricultural": {
        "TotalkWh": 4504370.0,
        "TotalCustomers": 123,
        "Combined": 0.0
      },
      "Elec- Commercial": {
        "TotalkWh": 0.0,
        "TotalCustomers": 0,
        "Combined": 0.0
      },
      "Elec- Industrial": {
        "TotalkWh": 0.0,
        "TotalCustomers": 0,
        "Combined": 0.0
      },
      "Elec- Residential": {
        "TotalkWh": 4836393.0,
        "TotalCustomers": 6320,
        "Combined": 0.0
      }
    },
    "2024": {
      "Elec- Agricultural": {
        "TotalkWh": 90001806.0,
        "TotalCustomers": 1034,
        "Combined": 0.0
      },
      "Elec- Commercial": {
        "TotalkWh": 0.0,
        "TotalCustomers": 0,
        "Combined": 0.0
      },
      "Elec- Industrial": {
        "TotalkWh": 0.0,
        "TotalCustomers": 0,
        "Combined": 0.0
      },
      "Elec- Residential": {
        "TotalkWh": 5168897.0,
        "TotalCustomers": 6241,
        "Combined": 0.0
      }
    }
  }
}