{
  "ZipCode": 93611,
  "Generated": "2025-06-02 16:42:58",
  "Project": "PGE_electric",
  "Years": {
    "2013": {
      "Elec- Agricultural": {
        "TotalkWh": 0.0,
        "TotalCustomers": 0,
        "Combined": 0.0
      },
      "Elec- Commercial": {
        "TotalkWh": 71629201.0,
        "TotalCustomers": 7791,
        "Combined": 0.0
      },
      "Elec- Industrial": {
        "TotalkWh": 0.0,
        "TotalCustomers": 0,
        "Combined": 0.0
      },
      "Elec- Residential": {
        "TotalkWh": 192193838.0,
        "TotalCustomers": 234509,
        "Combined": 0.0
      }
    },
    "2014": {
      "Elec- Agricultural": {
        "TotalkWh": 0.0,
        "TotalCustomers": 0,
        "Combined": 0.0
      },
      "Elec- Commercial": {
        "TotalkWh": 133805043.0,
        "TotalCustomers": 14854,
        "Combined": 0.0
      },
      "Elec- Industrial": {
        "TotalkWh": 0.0,
        "TotalCustomers": 0,
        "Combined": 0.0
      },
      "Elec- Residential": {
        "TotalkWh": 225451216.0,
        "TotalCustomers": 286698,
        "Combined": 0.0
      }
    },
    "2015": {
      "Elec- Agricultural": {
        "TotalkWh": 1320312.0,
        "TotalCustomers": 343,
        "Combined": 0.0
      },
      "Elec- Commercial": {
        "TotalkWh": 101906186.0,
        "TotalCustomers": 10878,
        "Combined": 0.0
      },
      "Elec- Industrial": {
        "TotalkWh": 0.0,
        "TotalCustomers": 0,
        "Combined": 0.0
      },
      "Elec- Residential": {
        "TotalkWh": 150415071.0,
        "TotalCustomers": 192961,
        "Combined": 0.0
      }
    },
    "2016": {
      "Elec- Agricultural": {
        "TotalkWh": 0.0,
        "TotalCustomers": 0,
        "Combined": 0.0
      },
      "Elec- Commercial": {
        "TotalkWh": 106348398.0,
        "TotalCustomers": 11649,
        "Combined": 0.0
      },
      "Elec- Industrial": {
        "TotalkWh": 0.0,
        "TotalCustomers": 0,
        "Combined": 0.0
      },
      "Elec- Residential": {
        "TotalkWh": 141245384.0,
        "TotalCustomers": 194326,
        "Combined": 0.0
      }
    },
    "2017": {
      "Elec- Agricultural": {
        "TotalkWh": 0.0,
        "TotalCustomers": 0,
        "Combined": 0.0
      },
      "Elec- Commercial": {
        "TotalkWh": 114198252.0,
        "TotalCustomers": 13189,
        "Combined": 0.0
      },
      "Elec- Industrial": {
        "TotalkWh": 0.0,
        "TotalCustomers": 0,
        "Combined": 0.0
      },
      "Elec- Residential": {
        "TotalkWh": 158250652.0,
        "TotalCustomers": 211767,
        "Combined": 0.0
      }
    },
    "2018": {
      "Elec- Agricultural": {
        "TotalkWh": 0.0,
        "TotalCustomers": 0,
        "Combined": 0.0
      },
      "Elec- Commercial": {
        "TotalkWh": 101157765.0,
        "TotalCustomers": 12443,
        "Combined": 0.0
      },
      "Elec- Industrial": {
        "TotalkWh": 0.0,
        "TotalCustomers": 0,
        "Combined": 0.0
      },
      "Elec- Residential": {
        "TotalkWh": 130346621.0,
        "TotalCustomers": 197016,
        "Combined": 0.0
      }
    },
    "2019": {
      "Elec- Agricultural": {
        "TotalkWh": 0.0,
        "TotalCustomers": 0,
        "Combined": 0.0
      },
      "Elec- Commercial": {
        "TotalkWh": 99316488.0,
        "TotalCustomers": 12757,
        "Combined": 0.0
      },
      "Elec- Industrial": {
        "TotalkWh": 0.0,
        "TotalCustomers": 0,
        "Combined": 0.0
      },
      "Elec- Residential": {
        "TotalkWh": 123113922.0,
        "TotalCustomers": 197746,
        "Combined": 0.0
      }
    },
    "2020": {
      "Elec- Agricultural": {
        "TotalkWh": 1103106.0,
        "TotalCustomers": 299,
        "Combined": 0.0
      },
      "Elec- Commercial": {
        "TotalkWh": 71444414.0,
        "TotalCustomers": 9610,
        "Combined": 0.0
      },
      "Elec- Industrial": {
        "TotalkWh": 0.0,
        "TotalCustomers": 0,
        "Combined": 0.0
      },
      "Elec- Residential": {
        "TotalkWh": 136098645.0,
        "TotalCustomers": 200343,
        "Combined": 0.0
      }
    },
    "2021": {
      "Elec- Agricultural": {
        "TotalkWh": 1191123.0,
        "TotalCustomers": 275,
        "Combined": 0.0
      },
      "Elec- Commercial": {
        "TotalkWh": 113046217.0,
        "TotalCustomers": 13696,
        "Combined": 0.0
      },
      "Elec- Industrial": {
        "TotalkWh": 0.0,
        "TotalCustomers": 0,
        "Combined": 0.0
      },
      "Elec- Residential": {
        "TotalkWh": 154185750.0,
        "TotalCustomers": 202106,
        "Combined": 0.0
      }
    },
    "2022": {
      "Elec- Agricultural": {
        "TotalkWh": 620474.0,
        "TotalCustomers": 146,
        "Combined": 0.0
      },
      "Elec- Commercial": {
        "TotalkWh": 115059481.0,
        "TotalCustomers": 13344,
        "Combined": 0.0
      },
      "Elec- Industrial": {
        "TotalkWh": 0.0,
        "TotalCustomers": 0,
        "Combined": 0.0
      },
      "Elec- Residential": {
        "TotalkWh": 157243889.0,
        "TotalCustomers": 201061,
        "Combined": 0.0
      }
    },
    "2023": {
      "Elec- Agricultural": {
        "TotalkWh": 803917.0,
        "TotalCustomers": 250,
        "Combined": 0.0
      },
      "Elec- Commercial": {
        "TotalkWh": 112836620.0,
        "TotalCustomers": 13417,
        "Combined": 0.0
      },
      "Elec- Industrial": {
        "TotalkWh": 0.0,
        "TotalCustomers": 0,
        "Combined": 0.0
      },
      "Elec- Residential": {
        "TotalkWh": 144021355.0,
        "TotalCustomers": 201258,
        "Combined": 0.0
      }
    },
    "2024": {
      "Elec- Agricultural": {
        "TotalkWh": 435085.0,
        "TotalCustomers": 118,
        "Combined": 0.0
      },
      "Elec- Commercial": {
        "TotalkWh": 123658685.0,
        "TotalCustomers": 13775,
        "Combined": 0.0
      },
      "Elec- Industrial": {
        "TotalkWh": 0.0,
        "TotalCustomers": 0,
        "Combined": 0.0
      },
      "Elec- Residential": {
        "TotalkWh": 152939796.0,
        "TotalCustomers": 202279,
        "Combined": 0.0
      }
    }
  }
}