{
  "ZipCode": 94608,
  "Generated": "2025-06-02 16:42:59",
  "Project": "PGE_electric",
  "Years": {
    "2013": {
      "Elec- Commercial": {
        "TotalkWh": 204620921.0,
        "TotalCustomers": 16736,
        "Combined": 0.0
      },
      "Elec- Industrial": {
        "TotalkWh": 0.0,
        "TotalCustomers": 0,
        "Combined": 0.0
      },
      "Elec- Residential": {
        "TotalkWh": 68092021.0,
        "TotalCustomers": 196829,
        "Combined": 0.0
      }
    },
    "2014": {
      "Elec- Commercial": {
        "TotalkWh": 263216665.0,
        "TotalCustomers": 25730,
        "Combined": 0.0
      },
      "Elec- Industrial": {
        "TotalkWh": 0.0,
        "TotalCustomers": 0,
        "Combined": 0.0
      },
      "Elec- Residential": {
        "TotalkWh": 75798926.0,
        "TotalCustomers": 240598,
        "Combined": 0.0
      }
    },
    "2015": {
      "Elec- Commercial": {
        "TotalkWh": 201064420.0,
        "TotalCustomers": 19903,
        "Combined": 0.0
      },
      "Elec- Industrial": {
        "TotalkWh": 0.0,
        "TotalCustomers": 0,
        "Combined": 0.0
      },
      "Elec- Residential": {
        "TotalkWh": 51017456.0,
        "TotalCustomers": 165094,
        "Combined": 0.0
      }
    },
    "2016": {
      "Elec- Commercial": {
        "TotalkWh": 211644505.0,
        "TotalCustomers": 20144,
        "Combined": 0.0
      },
      "Elec- Industrial": {
        "TotalkWh": 0.0,
        "TotalCustomers": 0,
        "Combined": 0.0
      },
      "Elec- Residential": {
        "TotalkWh": 51238591.0,
        "TotalCustomers": 167340,
        "Combined": 0.0
      }
    },
    "2017": {
      "Elec- Commercial": {
        "TotalkWh": 208096241.0,
        "TotalCustomers": 18213,
        "Combined": 0.0
      },
      "Elec- Industrial": {
        "TotalkWh": 0.0,
        "TotalCustomers": 0,
        "Combined": 0.0
      },
      "Elec- Residential": {
        "TotalkWh": 54897374.0,
        "TotalCustomers": 181982,
        "Combined": 0.0
      }
    },
    "2018": {
      "Elec- Commercial": {
        "TotalkWh": 212598979.0,
        "TotalCustomers": 20988,
        "Combined": 0.0
      },
      "Elec- Industrial": {
        "TotalkWh": 0.0,
        "TotalCustomers": 0,
        "Combined": 0.0
      },
      "Elec- Residential": {
        "TotalkWh": 50138935.0,
        "TotalCustomers": 169495,
        "Combined": 0.0
      }
    },
    "2019": {
      "Elec- Agricultural": {
        "TotalkWh": 0.0,
        "TotalCustomers": 0,
        "Combined": 0.0
      },
      "Elec- Commercial": {
        "TotalkWh": 209968154.0,
        "TotalCustomers": 20576,
        "Combined": 0.0
      },
      "Elec- Industrial": {
        "TotalkWh": 0.0,
        "TotalCustomers": 0,
        "Combined": 0.0
      },
      "Elec- Residential": {
        "TotalkWh": 50215491.0,
        "TotalCustomers": 171781,
        "Combined": 0.0
      }
    },
    "2020": {
      "Elec- Agricultural": {
        "TotalkWh": 0.0,
        "TotalCustomers": 0,
        "Combined": 0.0
      },
      "Elec- Commercial": {
        "TotalkWh": 198798971.0,
        "TotalCustomers": 21230,
        "Combined": 0.0
      },
      "Elec- Industrial": {
        "TotalkWh": 0.0,
        "TotalCustomers": 0,
        "Combined": 0.0
      },
      "Elec- Residential": {
        "TotalkWh": 55048152.0,
        "TotalCustomers": 174646,
        "Combined": 0.0
      }
    },
    "2021": {
      "Elec- Agricultural": {
        "TotalkWh": 0.0,
        "TotalCustomers": 0,
        "Combined": 0.0
      },
      "Elec- Commercial": {
        "TotalkWh": 176812542.0,
        "TotalCustomers": 15723,
        "Combined": 0.0
      },
      "Elec- Industrial": {
        "TotalkWh": 0.0,
        "TotalCustomers": 0,
        "Combined": 0.0
      },
      "Elec- Residential": {
        "TotalkWh": 55506019.0,
        "TotalCustomers": 176032,
        "Combined": 0.0
      }
    },
    "2022": {
      "Elec- Agricultural": {
        "TotalkWh": 0.0,
        "TotalCustomers": 0,
        "Combined": 0.0
      },
      "Elec- Commercial": {
        "TotalkWh": 252777172.0,
        "TotalCustomers": 23197,
        "Combined": 0.0
      },
      "Elec- Industrial": {
        "TotalkWh": 0.0,
        "TotalCustomers": 0,
        "Combined": 0.0
      },
      "Elec- Residential": {
        "TotalkWh": 54711225.0,
        "TotalCustomers": 177475,
        "Combined": 0.0
      }
    },
    "2023": {
      "Elec- Agricultural": {
        "TotalkWh": 0.0,
        "TotalCustomers": 0,
        "Combined": 0.0
      },
      "Elec- Commercial": {
        "TotalkWh": 332231642.0,
        "TotalCustomers": 31170,
        "Combined": 0.0
      },
      "Elec- Industrial": {
        "TotalkWh": 0.0,
        "TotalCustomers": 0,
        "Combined": 0.0
      },
      "Elec- Residential": {
        "TotalkWh": 56221611.0,
        "TotalCustomers": 180752,
        "Combined": 0.0
      }
    },
    "2024": {
      "Elec- Agricultural": {
        "TotalkWh": 0.0,
        "TotalCustomers": 0,
        "Combined": 0.0
      },
      "Elec- Commercial": {
        "TotalkWh": 380541854.0,
        "TotalCustomers": 38265,
        "Combined": 0.0
      },
      "Elec- Industrial": {
        "TotalkWh": 268862545.0,
        "TotalCustomers": 479,
        "Combined": 0.0
      },
      "Elec- Residential": {
        "TotalkWh": 54203773.0,
        "TotalCustomers": 183330,
        "Combined": 0.0
      }
    }
  }
}