{
  "ZipCode": 95128,
  "Generated": "2025-06-02 16:42:59",
  "Project": "PGE_electric",
  "Years": {
    "2013": {
      "Elec- Commercial": {
        "TotalkWh": 142822810.0,
        "TotalCustomers": 15299,
        "Combined": 0.0
      },
      "Elec- Industrial": {
        "TotalkWh": 0.0,
        "TotalCustomers": 0,
        "Combined": 0.0
      },
      "Elec- Residential": {
        "TotalkWh": 86173583.0,
        "TotalCustomers": 201114,
        "Combined": 0.0
      }
    },
    "2014": {
      "Elec- Commercial": {
        "TotalkWh": 185144224.0,
        "TotalCustomers": 19100,
        "Combined": 0.0
      },
      "Elec- Industrial": {
        "TotalkWh": 0.0,
        "TotalCustomers": 0,
        "Combined": 0.0
      },
      "Elec- Residential": {
        "TotalkWh": 98914889.0,
        "TotalCustomers": 244605,
        "Combined": 0.0
      }
    },
    "2015": {
      "Elec- Commercial": {
        "TotalkWh": 115808381.0,
        "TotalCustomers": 12211,
        "Combined": 0.0
      },
      "Elec- Industrial": {
        "TotalkWh": 0.0,
        "TotalCustomers": 0,
        "Combined": 0.0
      },
      "Elec- Residential": {
        "TotalkWh": 66319308.0,
        "TotalCustomers": 164349,
        "Combined": 0.0
      }
    },
    "2016": {
      "Elec- Commercial": {
        "TotalkWh": 121066909.0,
        "TotalCustomers": 12896,
        "Combined": 0.0
      },
      "Elec- Industrial": {
        "TotalkWh": 0.0,
        "TotalCustomers": 0,
        "Combined": 0.0
      },
      "Elec- Residential": {
        "TotalkWh": 64133780.0,
        "TotalCustomers": 164833,
        "Combined": 0.0
      }
    },
    "2017": {
      "Elec- Commercial": {
        "TotalkWh": 109097309.0,
        "TotalCustomers": 11425,
        "Combined": 0.0
      },
      "Elec- Industrial": {
        "TotalkWh": 0.0,
        "TotalCustomers": 0,
        "Combined": 0.0
      },
      "Elec- Residential": {
        "TotalkWh": 71071631.0,
        "TotalCustomers": 176050,
        "Combined": 0.0
      }
    },
    "2018": {
      "Elec- Commercial": {
        "TotalkWh": 120136716.0,
        "TotalCustomers": 12606,
        "Combined": 0.0
      },
      "Elec- Industrial": {
        "TotalkWh": 0.0,
        "TotalCustomers": 0,
        "Combined": 0.0
      },
      "Elec- Residential": {
        "TotalkWh": 61488922.0,
        "TotalCustomers": 162254,
        "Combined": 0.0
      }
    },
    "2019": {
      "Elec- Commercial": {
        "TotalkWh": 135247118.0,
        "TotalCustomers": 13546,
        "Combined": 0.0
      },
      "Elec- Industrial": {
        "TotalkWh": 0.0,
        "TotalCustomers": 0,
        "Combined": 0.0
      },
      "Elec- Residential": {
        "TotalkWh": 62894635.0,
        "TotalCustomers": 161724,
        "Combined": 0.0
      }
    },
    "2020": {
      "Elec- Commercial": {
        "TotalkWh": 121218788.0,
        "TotalCustomers": 13176,
        "Combined": 0.0
      },
      "Elec- Industrial": {
        "TotalkWh": 0.0,
        "TotalCustomers": 0,
        "Combined": 0.0
      },
      "Elec- Residential": {
        "TotalkWh": 69905147.0,
        "TotalCustomers": 161510,
        "Combined": 0.0
      }
    },
    "2021": {
      "Elec- Commercial": {
        "TotalkWh": 14314901.0,
        "TotalCustomers": 1177,
        "Combined": 0.0
      },
      "Elec- Industrial": {
        "TotalkWh": 0.0,
        "TotalCustomers": 0,
        "Combined": 0.0
      },
      "Elec- Residential": {
        "TotalkWh": 66596441.0,
        "TotalCustomers": 163419,
        "Combined": 0.0
      }
    },
    "2022": {
      "Elec- Commercial": {
        "TotalkWh": 48354614.0,
        "TotalCustomers": 4466,
        "Combined": 0.0
      },
      "Elec- Residential": {
        "TotalkWh": 66856034.0,
        "TotalCustomers": 166091,
        "Combined": 0.0
      }
    },
    "2023": {
      "Elec- Commercial": {
        "TotalkWh": 0.0,
        "TotalCustomers": 0,
        "Combined": 0.0
      },
      "Elec- Residential": {
        "TotalkWh": 66271058.0,
        "TotalCustomers": 167579,
        "Combined": 0.0
      }
    },
    "2024": {
      "Elec- Commercial": {
        "TotalkWh": 28755745.0,
        "TotalCustomers": 2068,
        "Combined": 0.0
      },
      "Elec- Industrial": {
        "TotalkWh": 0.0,
        "TotalCustomers": 0,
        "Combined": 0.0
      },
      "Elec- Residential": {
        "TotalkWh": 68591684.0,
        "TotalCustomers": 170915,
        "Combined": 0.0
      }
    }
  }
}