{
  "ZipCode": 95637,
  "Generated": "2025-06-02 16:43:00",
  "Project": "PGE_electric",
  "Years": {
    "2013": {
      "Elec- Agricultural": {
        "TotalkWh": 797222.0,
        "TotalCustomers": 183,
        "Combined": 0.0
      },
      "Elec- Commercial": {
        "TotalkWh": 0.0,
        "TotalCustomers": 0,
        "Combined": 0.0
      },
      "Elec- Residential": {
        "TotalkWh": 1934377.0,
        "TotalCustomers": 2412,
        "Combined": 0.0
      }
    },
    "2014": {
      "Elec- Agricultural": {
        "TotalkWh": 1927348.0,
        "TotalCustomers": 325,
        "Combined": 0.0
      },
      "Elec- Commercial": {
        "TotalkWh": 0.0,
        "TotalCustomers": 0,
        "Combined": 0.0
      },
      "Elec- Residential": {
        "TotalkWh": 2119670.0,
        "TotalCustomers": 2930,
        "Combined": 0.0
      }
    },
    "2015": {
      "Elec- Agricultural": {
        "TotalkWh": 2195898.0,
        "TotalCustomers": 334,
        "Combined": 0.0
      },
      "Elec- Commercial": {
        "TotalkWh": 0.0,
        "TotalCustomers": 0,
        "Combined": 0.0
      },
      "Elec- Residential": {
        "TotalkWh": 1447807.0,
        "TotalCustomers": 1963,
        "Combined": 0.0
      }
    },
    "2016": {
      "Elec- Agricultural": {
        "TotalkWh": 1452849.0,
        "TotalCustomers": 398,
        "Combined": 0.0
      },
      "Elec- Commercial": {
        "TotalkWh": 0.0,
        "TotalCustomers": 0,
        "Combined": 0.0
      },
      "Elec- Residential": {
        "TotalkWh": 1480814.0,
        "TotalCustomers": 1948,
        "Combined": 0.0
      }
    },
    "2017": {
      "Elec- Agricultural": {
        "TotalkWh": 1725232.0,
        "TotalCustomers": 242,
        "Combined": 0.0
      },
      "Elec- Commercial": {
        "TotalkWh": 0.0,
        "TotalCustomers": 0,
        "Combined": 0.0
      },
      "Elec- Residential": {
        "TotalkWh": 1903290.0,
        "TotalCustomers": 2119,
        "Combined": 0.0
      }
    },
    "2018": {
      "Elec- Agricultural": {
        "TotalkWh": 3062558.0,
        "TotalCustomers": 500,
        "Combined": 0.0
      },
      "Elec- Commercial": {
        "TotalkWh": 0.0,
        "TotalCustomers": 0,
        "Combined": 0.0
      },
      "Elec- Residential": {
        "TotalkWh": 1714381.0,
        "TotalCustomers": 1972,
        "Combined": 0.0
      }
    },
    "2019": {
      "Elec- Agricultural": {
        "TotalkWh": 1358542.0,
        "TotalCustomers": 230,
        "Combined": 0.0
      },
      "Elec- Commercial": {
        "TotalkWh": 0.0,
        "TotalCustomers": 0,
        "Combined": 0.0
      },
      "Elec- Residential": {
        "TotalkWh": 1626602.0,
        "TotalCustomers": 1971,
        "Combined": 0.0
      }
    },
    "2020": {
      "Elec- Agricultural": {
        "TotalkWh": 1812213.0,
        "TotalCustomers": 236,
        "Combined": 0.0
      },
      "Elec- Commercial": {
        "TotalkWh": 0.0,
        "TotalCustomers": 0,
        "Combined": 0.0
      },
      "Elec- Residential": {
        "TotalkWh": 1752096.0,
        "TotalCustomers": 1968,
        "Combined": 0.0
      }
    },
    "2021": {
      "Elec- Agricultural": {
        "TotalkWh": 2494550.0,
        "TotalCustomers": 332,
        "Combined": 0.0
      },
      "Elec- Commercial": {
        "TotalkWh": 0.0,
        "TotalCustomers": 0,
        "Combined": 0.0
      },
      "Elec- Residential": {
        "TotalkWh": 1974819.0,
        "TotalCustomers": 1947,
        "Combined": 0.0
      }
    },
    "2022": {
      "Elec- Agricultural": {
        "TotalkWh": 700123.0,
        "TotalCustomers": 115,
        "Combined": 0.0
      },
      "Elec- Commercial": {
        "TotalkWh": 0.0,
        "TotalCustomers": 0,
        "Combined": 0.0
      },
      "Elec- Residential": {
        "TotalkWh": 2221558.0,
        "TotalCustomers": 2338,
        "Combined": 0.0
      }
    },
    "2023": {
      "Elec- Agricultural": {
        "TotalkWh": 341948.0,
        "TotalCustomers": 72,
        "Combined": 0.0
      },
      "Elec- Commercial": {
        "TotalkWh": 0.0,
        "TotalCustomers": 0,
        "Combined": 0.0
      },
      "Elec- Residential": {
        "TotalkWh": 3576449.0,
        "TotalCustomers": 3113,
        "Combined": 0.0
      }
    },
    "2024": {
      "Elec- Agricultural": {
        "TotalkWh": 1345140.0,
        "TotalCustomers": 356,
        "Combined": 0.0
      },
      "Elec- Commercial": {
        "TotalkWh": 0.0,
        "TotalCustomers": 0,
        "Combined": 0.0
      },
      "Elec- Residential": {
        "TotalkWh": 3515942.0,
        "TotalCustomers": 3114,
        "Combined": 0.0
      }
    }
  }
}