{
  "ZipCode": 95368,
  "Generated": "2025-06-02 16:51:02",
  "Project": "PGE_gas",
  "Years": {
    "2013": {
      "Gas- Commercial": {
        "TotalTHM": 0.0,
        "TotalCustomers": 0,
        "Combined": 0.0
      },
      "Gas- Residential": {
        "TotalTHM": 2176432.0,
        "TotalCustomers": 60233,
        "Combined": 0.0
      }
    },
    "2014": {
      "Gas- Commercial": {
        "TotalTHM": 0.0,
        "TotalCustomers": 0,
        "Combined": 0.0
      },
      "Gas- Residential": {
        "TotalTHM": 2070112.0,
        "TotalCustomers": 72487,
        "Combined": 0.0
      }
    },
    "2015": {
      "Gas- Commercial": {
        "TotalTHM": 0.0,
        "TotalCustomers": 0,
        "Combined": 0.0
      },
      "Gas- Residential": {
        "TotalTHM": 1454929.0,
        "TotalCustomers": 48449,
        "Combined": 0.0
      }
    },
    "2016": {
      "Gas- Commercial": {
        "TotalTHM": 0.0,
        "TotalCustomers": 0,
        "Combined": 0.0
      },
      "Gas- Residential": {
        "TotalTHM": 1415403.0,
        "TotalCustomers": 48420,
        "Combined": 0.0
      }
    },
    "2017": {
      "Gas- Commercial": {
        "TotalTHM": 0.0,
        "TotalCustomers": 0,
        "Combined": 0.0
      },
      "Gas- Residential": {
        "TotalTHM": 1534688.0,
        "TotalCustomers": 52592,
        "Combined": 0.0
      }
    },
    "2018": {
      "Gas- Commercial": {
        "TotalTHM": 0.0,
        "TotalCustomers": 0,
        "Combined": 0.0
      },
      "Gas- Residential": {
        "TotalTHM": 1484225.0,
        "TotalCustomers": 48462,
        "Combined": 0.0
      }
    },
    "2019": {
      "Gas- Commercial": {
        "TotalTHM": 0.0,
        "TotalCustomers": 0,
        "Combined": 0.0
      },
      "Gas- Residential": {
        "TotalTHM": 1545189.0,
        "TotalCustomers": 48341,
        "Combined": 0.0
      }
    },
    "2020": {
      "Gas- Commercial": {
        "TotalTHM": 0.0,
        "TotalCustomers": 0,
        "Combined": 0.0
      },
      "Gas- Residential": {
        "TotalTHM": 1591638.0,
        "TotalCustomers": 48073,
        "Combined": 0.0
      }
    },
    "2021": {
      "Gas- Commercial": {
        "TotalTHM": 0.0,
        "TotalCustomers": 0,
        "Combined": 0.0
      },
      "Gas- Residential": {
        "TotalTHM": 1541341.0,
        "TotalCustomers": 48036,
        "Combined": 0.0
      }
    },
    "2022": {
      "Gas- Commercial": {
        "TotalTHM": 0.0,
        "TotalCustomers": 0,
        "Combined": 0.0
      },
      "Gas- Residential": {
        "TotalTHM": 1566679.0,
        "TotalCustomers": 47882,
        "Combined": 0.0
      }
    },
    "2023": {
      "Gas- Commercial": {
        "TotalTHM": 0.0,
        "TotalCustomers": 0,
        "Combined": 0.0
      },
      "Gas- Residential": {
        "TotalTHM": 1442271.0,
        "TotalCustomers": 40212,
        "Combined": 0.0
      }
    },
    "2024": {
      "Gas- Commercial": {
        "TotalTHM": 37446.0,
        "TotalCustomers": 105,
        "Combined": 0.0
      },
      "Gas- Residential": {
        "TotalTHM": 1423227.0,
        "TotalCustomers": 48225,
        "Combined": 0.0
      }
    }
  }
}